pretty_print_json/__init__.py
pretty_print_json/__main__.py
pretty_print_json-2.0.3.dist-info/DESCRIPTION.rst
pretty_print_json-2.0.3.dist-info/entry_points.txt
pretty_print_json-2.0.3.dist-info/METADATA
pretty_print_json-2.0.3.dist-info/metadata.json
pretty_print_json-2.0.3.dist-info/RECORD
pretty_print_json-2.0.3.dist-info/top_level.txt
pretty_print_json-2.0.3.dist-info/WHEEL
