Metadata-Version: 2.0
Name: pretty-print-json
Version: 2.0.3
Summary: Tool for printing pretty JSON
Home-page: http://andrewshay.me
Author: Andrew Shay
Author-email: andrew.shay@andrewshay.me
License: MIT
Platform: UNKNOWN
Classifier: Development Status :: 5 - Production/Stable
Classifier: Intended Audience :: Developers
Classifier: Programming Language :: Python :: 2.7
Classifier: Programming Language :: Python :: 3.5
